sparsimony/__init__.py
sparsimony/distributions/__init__.py
sparsimony/distributions/base.py
sparsimony/dst/__init__.py
sparsimony/dst/base.py
sparsimony/dst/local_overparametrization.py
sparsimony/dst/rigl.py
sparsimony/dst/set.py
sparsimony/meta_tensor.py
sparsimony/nn_init.py
sparsimony/optim/__init__.py
sparsimony/optim/optim_wrapper.py
sparsimony/optim/type_registry.py
sparsimony/parametrization/__init__.py
sparsimony/parametrization/fake_sparsity.py
sparsimony/pruners/__init__.py
sparsimony/pruners/base.py
sparsimony/pruners/block.py
sparsimony/pruners/fine_grained.py
sparsimony/pruners/functional.py
sparsimony/pruners/neuron.py
sparsimony/pruners/unstructured.py
sparsimony/schedulers/__init__.py
sparsimony/schedulers/base.py
sparsimony/utils.py
sparsimony-0.1.0.dist-info/LICENSE
sparsimony-0.1.0.dist-info/METADATA
sparsimony-0.1.0.dist-info/WHEEL
sparsimony-0.1.0.dist-info/RECORD
