Metadata-Version: 2.1
Name: sparsimony
Version: 0.1.0
Summary: 
Home-page: https://github.com/mklasby/sparsimony
License: MIT
Author: Mike Lasby
Requires-Python: >=3.9,<=3.12
Classifier: Development Status :: 3 - Alpha
Classifier: Intended Audience :: Developers
Classifier: License :: OSI Approved :: MIT License
Classifier: Operating System :: OS Independent
Classifier: Programming Language :: Python
Classifier: Programming Language :: Python :: 3
Classifier: Programming Language :: Python :: 3.9
Classifier: Programming Language :: Python :: 3.10
Classifier: Programming Language :: Python :: 3.11
Classifier: Programming Language :: Python :: 3.12
Classifier: Topic :: Software Development :: Libraries :: Python Modules
Requires-Dist: numpy (==1.*)
Requires-Dist: torch (>=2.0)
Project-URL: Issues, https://github.com/mklasby/sparsimony/issues
Project-URL: Repo, https://github.com/mklasby/sparsimony
